diffome/__init__.py
diffome/connectome/__init__.py
diffome/connectome/base.py
diffome/tda/__init__.py
diffome/tda/barcode.py
diffome/tda/compare.py
diffome/tda/wasser.py
diffome/viz/__init__.py
diffome-0.1.0.dist-info/METADATA
diffome-0.1.0.dist-info/WHEEL
diffome-0.1.0.dist-info/top_level.txt
diffome-0.1.0.dist-info/RECORD
